{
  "schemaVersion": 1,
  "id": "serversimplified",
  "version": "${version}",

  "name": "Server Simplified",
  "description": "Adds simple commands for server owners. Originally developed by zeroeightysix, yitzy299 has continued development",
  "authors": [
    "yitzy299", "zeroeightysix"
  ],
  "contact": {
    "homepage": "https://github.com/yitzy299/server-simplified/releases",
    "sources": "https://github.com/yitzy299/server-simplified/"
  },

  "license": "GPL-3.0",
  "icon": "assets/serversimplified/icon.png",

  "environment": "*", 
  "entrypoints": {
    "main": [
      "tech.dttp.serversimplified.ServerSimplified"
    ]
  },
  "mixins": [
    "serversimplified.mixins.json"
  ],

  "depends": {
    "fabricloader": ">=0.10.6",
    "fabric": ">=0.25.1"
  },
  "suggests": {
    "another-mod": "blocklogger"
  }
}
